{
  "cash": 954331.2539999998,
  "positions": {
    "000338": {
      "symbol": "000338",
      "quantity": 300,
      "avg_price": 25.9175,
      "cost": 10369.594,
      "buy_date": "2026-03-11",
      "available_quantity": 0,
      "market_value": 7494.0,
      "current_price": 24.98,
      "pnl": -281.25,
      "pnl_rate": -3.617247033857432
    },
    "002475": {
      "symbol": "002475",
      "quantity": 100,
      "avg_price": 50.05657142857143,
      "cost": 175203.011,
      "buy_date": "2026-03-11",
      "available_quantity": 100,
      "market_value": 4921.0,
      "current_price": 49.21,
      "pnl": -84.65714285714299,
      "pnl_rate": -1.6912293519332438
    },
    "600111": {
      "symbol": "600111",
      "name": "北方稀土",
      "quantity": 700,
      "avg_price": 49.01,
      "current_price": 48.73,
      "market_value": 34111.0,
      "pnl": -196.0000000000008,
      "pnl_rate": -0.5713119771475232
    }
  },
  "initial_capital": 1000000,
  "created_at": "2026-03-11T12:59:12.452652",
  "market_value": 46526.0,
  "total_assets": 1000857.2539999998,
  "total_pnl": -561.9071428571438,
  "realtime_prices": {
    "000338": 24.98,
    "002475": 49.21,
    "600111": 48.73
  },
  "updated_at": "2026-03-18T09:50:42.447376"
}